cj_google_scraper/__init__.py
cj_google_scraper/connect.py
cj_google_scraper/example.py
cj_google_scraper/scripts.py
cj_google_scraper/util.py
cj_google_scraper/shopping/__init__.py
cj_google_scraper/shopping/sample_url.py
cj_google_scraper/shopping/scraper.py
cj_google_scraper-0.0.1.dist-info/METADATA
cj_google_scraper-0.0.1.dist-info/WHEEL
cj_google_scraper-0.0.1.dist-info/entry_points.txt
cj_google_scraper-0.0.1.dist-info/top_level.txt
cj_google_scraper-0.0.1.dist-info/RECORD
