Metadata-Version: 2.1
Name: cj_google_scraper
Version: 0.0.1
Author: Woojin Cho
Author-email: w.cho@cj.net
License: MIT License
Requires-Python: >=3.9
Requires-Dist: beautifulsoup4
Requires-Dist: click
Requires-Dist: fastnumbers
Requires-Dist: parse
Requires-Dist: pillow
Requires-Dist: selenium
Requires-Dist: webdriver-manager
